psx/__init__.py
psx-0.0.1.dist-info/METADATA
psx-0.0.1.dist-info/WHEEL
psx-0.0.1.dist-info/licenses/LICENSE
psx-0.0.1.dist-info/RECORD
